odoo/addons/storage_image_product_pos/README.rst
odoo/addons/storage_image_product_pos/__init__.py
odoo/addons/storage_image_product_pos/__manifest__.py
odoo/addons/storage_image_product_pos/i18n/storage_image_product_pos.pot
odoo/addons/storage_image_product_pos/readme/CONTRIBUTORS.rst
odoo/addons/storage_image_product_pos/readme/DESCRIPTION.rst
odoo/addons/storage_image_product_pos/readme/INSTALLATION.rst
odoo/addons/storage_image_product_pos/static/description/icon.png
odoo/addons/storage_image_product_pos/static/description/index.html
odoo/addons/storage_image_product_pos/static/src/js/Chrome.js
odoo/addons/storage_image_product_pos/static/src/js/ProductItem.js
odoo/addons/storage_image_product_pos/static/src/js/models.js
odoo/addons/storage_image_product_pos/views/pos_product.xml
odoo14_addon_storage_image_product_pos-14.0.1.1.0.dist-info/METADATA
odoo14_addon_storage_image_product_pos-14.0.1.1.0.dist-info/WHEEL
odoo14_addon_storage_image_product_pos-14.0.1.1.0.dist-info/top_level.txt
odoo14_addon_storage_image_product_pos-14.0.1.1.0.dist-info/RECORD
